src/__init__.py
src/salutation.py
fem_kit-2022.0.dist-info/LICENSE
fem_kit-2022.0.dist-info/WHEEL
fem_kit-2022.0.dist-info/METADATA
fem_kit-2022.0.dist-info/RECORD
